cyberfusion/PowerDNSSecondaryCleaner/CLI.py
cyberfusion/PowerDNSSecondaryCleaner/__init__.py
cyberfusion/PowerDNSSecondaryCleaner/powerdns_api.py
python3_cyberfusion_powerdns_secondary_cleaner-1.1.dist-info/METADATA
python3_cyberfusion_powerdns_secondary_cleaner-1.1.dist-info/WHEEL
python3_cyberfusion_powerdns_secondary_cleaner-1.1.dist-info/entry_points.txt
python3_cyberfusion_powerdns_secondary_cleaner-1.1.dist-info/top_level.txt
python3_cyberfusion_powerdns_secondary_cleaner-1.1.dist-info/RECORD
