Metadata-Version: 2.4
Name: python3-cyberfusion-powerdns-secondary-cleaner
Version: 1.1
Summary: Use powerdns-secondary-cleaner to delete zones on secondary PowerDNS server that were deleted on primary PowerDNS server.
Author-email: Cyberfusion <support@cyberfusion.io>
Project-URL: Source, https://github.com/CyberfusionIO/python3-cyberfusion-powerdns-secondary-cleaner
Requires-Dist: docopt==0.6.2
Requires-Dist: schema==0.7.7
Requires-Dist: requests==2.32.3
